marzneshin/__init__.py
marzneshin/api.py
marzneshin/models.py
marzneshin-0.1.3.dist-info/LICENSE
marzneshin-0.1.3.dist-info/WHEEL
marzneshin-0.1.3.dist-info/METADATA
marzneshin-0.1.3.dist-info/RECORD
