Metadata-Version: 2.1
Name: marzneshin
Version: 0.1.3
Summary: Marzneshin Control API Client
Home-page: https://github.com/sm1ky/marzneshin_api
Author: Artem
Author-email: contact@sm1ky.com
Requires-Python: >=3.10
Requires-Dist: httpx
Requires-Dist: pydantic
